{"cameraMode":{"drawMode":0,"name":"Shaded","section":"Shading Mode"},"sceneLighting":true,"audioPlay":false,"sceneViewState":{"m_AlwaysRefresh":false,"showFog":true,"showSkybox":true,"showFlares":true,"showImageEffects":true,"showParticleSystems":true,"showVisualEffectGraphs":true,"m_FxEnabled":true},"in2DMode":false,"pivot":{"x":1.0264824628829957,"y":0.6551899313926697,"z":-37.803253173828128},"rotation":{"x":0.006900837644934654,"y":0.9918025135993958,"z":-0.11205068975687027,"w":0.06107432767748833},"size":0.06506088376045227,"orthographic":false}